DLMSAdapter/__init__.py
DLMSAdapter/main.py
DLMSAdapter/pool.py
DLMSAdapter/xml_.py
dlmsadapter-0.7.9.dist-info/METADATA
dlmsadapter-0.7.9.dist-info/WHEEL
dlmsadapter-0.7.9.dist-info/entry_points.txt
dlmsadapter-0.7.9.dist-info/top_level.txt
dlmsadapter-0.7.9.dist-info/RECORD
