Metadata-Version: 2.4
Name: DLMSAdapter
Version: 0.7.9
Summary: dlms-spodes
Author-email: Serj Kotilevski <youserj@outlook.com>
Project-URL: Source, https://github.com/youserj/SPODESclient_prj
Keywords: dlms,spodes,adapter
Classifier: Programming Language :: Python :: 3
Classifier: License :: OSI Approved :: MIT License
Classifier: Operating System :: OS Independent
Requires-Python: >=3.12
Requires-Dist: DLMS-SPODES<0.89,>=0.87.8
Requires-Dist: StructResult>=0.9.2
Requires-Dist: semver>=3.0.2
Provides-Extra: dev
Requires-Dist: mypy>=1.5.0; extra == "dev"
Requires-Dist: ruff>=0.11; extra == "dev"
Requires-Dist: types-requests; extra == "dev"
